{
  "alexander-the-great": {
    "hash": "b9ad6fee9e575cba37cc",
    "seriesStub": "alexander-the-great",
    "seriesTitle": "Alexander The Great",
    "topicTitle": "Alexander The Great",
    "aliases": [],
    "cachedAt": "2025-10-28T15:36:47.445Z"
  },
  "moments-fall-of-the-roman-republic": {
    "hash": "12d898c65bb97f8b2dda",
    "seriesStub": "moments-fall-of-the-roman-republic",
    "seriesTitle": "Moments: Fall Of The Roman Republic",
    "topicTitle": "Moments",
    "aliases": [],
    "cachedAt": "2025-10-28T15:36:47.445Z"
  }
}
